odoo/addons/mail_template_multi_company/README.rst
odoo/addons/mail_template_multi_company/__init__.py
odoo/addons/mail_template_multi_company/__manifest__.py
odoo/addons/mail_template_multi_company/i18n/es.po
odoo/addons/mail_template_multi_company/i18n/mail_template_multi_company.pot
odoo/addons/mail_template_multi_company/migrations/13.0.1.0.0/post-migration.py
odoo/addons/mail_template_multi_company/models/__init__.py
odoo/addons/mail_template_multi_company/models/mail_template.py
odoo/addons/mail_template_multi_company/readme/CONFIGURE.rst
odoo/addons/mail_template_multi_company/readme/CONTRIBUTORS.rst
odoo/addons/mail_template_multi_company/readme/DESCRIPTION.rst
odoo/addons/mail_template_multi_company/readme/USAGE.rst
odoo/addons/mail_template_multi_company/security/mail_template.xml
odoo/addons/mail_template_multi_company/static/description/icon.png
odoo/addons/mail_template_multi_company/static/description/index.html
odoo/addons/mail_template_multi_company/views/mail_template.xml
odoo13_addon_mail_template_multi_company-13.0.1.0.1.dev5.dist-info/METADATA
odoo13_addon_mail_template_multi_company-13.0.1.0.1.dev5.dist-info/WHEEL
odoo13_addon_mail_template_multi_company-13.0.1.0.1.dev5.dist-info/top_level.txt
odoo13_addon_mail_template_multi_company-13.0.1.0.1.dev5.dist-info/RECORD
